CHANGES.rst
README.rst
setup.cfg
setup.py
deform_widget_dynatree/__init__.py
deform_widget_dynatree.egg-info/PKG-INFO
deform_widget_dynatree.egg-info/SOURCES.txt
deform_widget_dynatree.egg-info/dependency_links.txt
deform_widget_dynatree.egg-info/not-zip-safe
deform_widget_dynatree.egg-info/requires.txt
deform_widget_dynatree.egg-info/top_level.txt
deform_widget_dynatree/static/jquery-ui.custom.js
deform_widget_dynatree/static/jquery-ui.custom.min.js
deform_widget_dynatree/static/jquery.cookie.js
deform_widget_dynatree/static/jquery.dynatree.js
deform_widget_dynatree/static/jquery.dynatree.min.js
deform_widget_dynatree/static/jquery.js
deform_widget_dynatree/static/jquery.min.js
deform_widget_dynatree/templates/dynatree.pt
deform_widget_dynatree/templates/readonly/dynatree.pt