Metadata-Version: 1.0
Name: deform-widget-dynatree
Version: 0.1dev
Summary: jQuery dynatree widget for deform
Home-page: https://github.com/disko/deform_widget_dynatree
Author: Andreas Kaiser
Author-email: disko@binary-punks.com
License: BSD
Keywords: deform widget
Platform: UNKNOWN
Classifier: Development Status :: 5 - Production/Stable
Classifier: Environment :: Web Environment
Classifier: Framework :: Pylons
Classifier: Framework :: Pyramid
Classifier: Intended Audience :: Developers
Classifier: License :: OSI Approved :: BSD License
Classifier: Natural Language :: English
Classifier: Operating System :: OS Independent
Classifier: Programming Language :: JavaScript
Classifier: Programming Language :: Python
Classifier: Programming Language :: Python :: 2.6
Classifier: Programming Language :: Python :: 2.7
Classifier: Topic :: Internet
Classifier: Topic :: Software Development :: User Interfaces
Classifier: Topic :: Software Development :: Widget Sets
